aiohttp_aiocache/__init__.py
aiohttp_aiocache/_api.py
aiohttp_aiocache/_middleware.py
aiohttp_aiocache/_utils.py
aiohttp_aiocache/py.typed
aiohttp_aiocache-0.1.0.dist-info/LICENSE
aiohttp_aiocache-0.1.0.dist-info/WHEEL
aiohttp_aiocache-0.1.0.dist-info/METADATA
aiohttp_aiocache-0.1.0.dist-info/RECORD
