Metadata-Version: 2.1
Name: aiohttp-aiocache
Version: 0.1.0
Summary: Caching middleware for aiohttp server with aiocache under the hood
Home-page: https://github.com/nobbynobbs/aiohttp-aiocache
License: MIT
Keywords: cache,aiohttp,redis,memcached
Author: Roman Bolkhovitin
Author-email: rbolkhovitin@gmail.com
Requires-Python: >=3.6,<4.0
Classifier: Development Status :: 4 - Beta
Classifier: Intended Audience :: Developers
Classifier: License :: OSI Approved :: MIT License
Classifier: Operating System :: OS Independent
Classifier: Programming Language :: Python :: 3
Classifier: Programming Language :: Python :: 3.6
Classifier: Programming Language :: Python :: 3.7
Classifier: Programming Language :: Python :: 3.8
Classifier: Typing :: Typed
Requires-Dist: aiocache (>=0.11.1,<0.12.0)
Project-URL: Repository, https://github.com/nobbynobbs/aiohttp-aiocache
